gprmaxui/__init__.py
gprmaxui/gprmax_model.py
gprmaxui/plotter.py
gprmaxui/utils.py
gprmaxui/commands/__init__.py
gprmaxui/commands/commands_parser.py
gprmaxui/commands/domain_commands.py
gprmaxui/commands/geometry_commands.py
gprmaxui/commands/sources_commands.py
gprmaxui-1.0.0.dist-info/METADATA
gprmaxui-1.0.0.dist-info/WHEEL
gprmaxui-1.0.0.dist-info/licenses/LICENSE
gprmaxui-1.0.0.dist-info/RECORD
