Metadata-Version: 2.4
Name: gprmaxui
Version: 1.0.0
Summary: Add your description here
License-File: LICENSE
Requires-Python: >=3.10
Requires-Dist: cython>=3.0.11
Requires-Dist: h5py>=3.12.1
Requires-Dist: httpcore>=1.0.6
Requires-Dist: more-itertools>=10.5.0
Requires-Dist: opencv-python>=4.10.0.84
Requires-Dist: pillow>=10.4.0
Requires-Dist: psutil>=6.0.0
Requires-Dist: pydantic>=2.9.2
Requires-Dist: pyside6>=6.8.0.1
Requires-Dist: pyvista[all]>=0.44.1
Requires-Dist: pyvistaqt>=0.11.1
Requires-Dist: rich>=13.9.2
Requires-Dist: scipy>=1.14.1
Requires-Dist: terminaltables>=3.1.10
Requires-Dist: tqdm>=4.66.5
Requires-Dist: xmltodict>=0.14.1
Provides-Extra: demos
Requires-Dist: notebook>=7.4.3; extra == 'demos'
Requires-Dist: panel>=1.7.1; extra == 'demos'
Provides-Extra: gpu
Requires-Dist: pycuda>=2025.1; extra == 'gpu'
